<annotation>
	<folder>imageset</folder>
	<filename>1650900656682.png</filename>
	<path>C:\Users\Heymax\Desktop\imageset\1650900656682.png</path>
	<source>
		<database>Unknown</database>
	</source>
	<size>
		<width>1920</width>
		<height>1080</height>
		<depth>3</depth>
	</size>
	<segmented>0</segmented>
	<object>
		<name>caster</name>
		<pose>Unspecified</pose>
		<truncated>0</truncated>
		<difficult>0</difficult>
		<bndbox>
			<xmin>695</xmin>
			<ymin>300</ymin>
			<xmax>951</xmax>
			<ymax>535</ymax>
		</bndbox>
	</object>
	<object>
		<name>hili</name>
		<pose>Unspecified</pose>
		<truncated>0</truncated>
		<difficult>0</difficult>
		<bndbox>
			<xmin>1134</xmin>
			<ymin>266</ymin>
			<xmax>1265</xmax>
			<ymax>396</ymax>
		</bndbox>
	</object>
</annotation>
