<annotation>
	<folder>imageset</folder>
	<filename>1650640645593.png</filename>
	<path>C:\Users\Heymax\Desktop\imageset\1650640645593.png</path>
	<source>
		<database>Unknown</database>
	</source>
	<size>
		<width>1920</width>
		<height>1080</height>
		<depth>3</depth>
	</size>
	<segmented>0</segmented>
	<object>
		<name>character</name>
		<pose>Unspecified</pose>
		<truncated>0</truncated>
		<difficult>0</difficult>
		<bndbox>
			<xmin>791</xmin>
			<ymin>385</ymin>
			<xmax>1141</xmax>
			<ymax>798</ymax>
		</bndbox>
	</object>
</annotation>
