<annotation>
	<folder>imageset</folder>
	<filename>1651074421360.png</filename>
	<path>C:\Users\Heymax\Desktop\imageset\1651074421360.png</path>
	<source>
		<database>Unknown</database>
	</source>
	<size>
		<width>1920</width>
		<height>1080</height>
		<depth>3</depth>
	</size>
	<segmented>0</segmented>
	<object>
		<name>bighili</name>
		<pose>Unspecified</pose>
		<truncated>0</truncated>
		<difficult>0</difficult>
		<bndbox>
			<xmin>1129</xmin>
			<ymin>267</ymin>
			<xmax>1648</xmax>
			<ymax>823</ymax>
		</bndbox>
	</object>
	<object>
		<name>bighili</name>
		<pose>Unspecified</pose>
		<truncated>0</truncated>
		<difficult>0</difficult>
		<bndbox>
			<xmin>743</xmin>
			<ymin>232</ymin>
			<xmax>1020</xmax>
			<ymax>491</ymax>
		</bndbox>
	</object>
</annotation>
